odoo/addons/stock_picking_send_by_mail/README.rst
odoo/addons/stock_picking_send_by_mail/__init__.py
odoo/addons/stock_picking_send_by_mail/__manifest__.py
odoo/addons/stock_picking_send_by_mail/i18n/de.po
odoo/addons/stock_picking_send_by_mail/i18n/es.po
odoo/addons/stock_picking_send_by_mail/i18n/fr.po
odoo/addons/stock_picking_send_by_mail/i18n/it.po
odoo/addons/stock_picking_send_by_mail/i18n/pt_BR.po
odoo/addons/stock_picking_send_by_mail/i18n/stock_picking_send_by_mail.pot
odoo/addons/stock_picking_send_by_mail/models/__init__.py
odoo/addons/stock_picking_send_by_mail/models/stock_picking.py
odoo/addons/stock_picking_send_by_mail/readme/CONTRIBUTORS.rst
odoo/addons/stock_picking_send_by_mail/readme/DESCRIPTION.rst
odoo/addons/stock_picking_send_by_mail/readme/USAGE.rst
odoo/addons/stock_picking_send_by_mail/static/description/icon.png
odoo/addons/stock_picking_send_by_mail/static/description/index.html
odoo/addons/stock_picking_send_by_mail/tests/__init__.py
odoo/addons/stock_picking_send_by_mail/tests/test_stock_picking_send_by_mail.py
odoo/addons/stock_picking_send_by_mail/views/stock_picking_view.xml
odoo14_addon_stock_picking_send_by_mail-14.0.1.0.1.dev7.dist-info/METADATA
odoo14_addon_stock_picking_send_by_mail-14.0.1.0.1.dev7.dist-info/WHEEL
odoo14_addon_stock_picking_send_by_mail-14.0.1.0.1.dev7.dist-info/top_level.txt
odoo14_addon_stock_picking_send_by_mail-14.0.1.0.1.dev7.dist-info/RECORD
